sparkplus/__init__.py
sparkplus/core/__init__.py
sparkplus/core/base.py
sparkplus/core/coord_dataframe.py
sparkplus/core/job.py
sparkplus/core/py_log.py
sparkplus/core/roadname_dataframe.py
sparkplus/core/shp_to_parquet.py
sparkplus/core/udfs.py
sparkplus/dependencies/__init__.py
sparkplus/dependencies/logging.py
sparkplus/dependencies/spark.py
sparkplus/dependencies/tablename.py
sparkplus/jobs/__init__.py
sparkplus/jobs/conversion.py
sparkplus/jobs/etl_job.py
sparkplus/jobs/load_database.py
sparkplus/jobs/table_to_df.py
sparkplus/jobs/with_geopandas.py
sparkplus/package/__init__.py
sparkplus/package/gis.py
sparkplus/package/pipeline.py
sparkplus/resource/.DS_Store
sparkplus/resource/EMD_202101/TL_SCCO_EMD.dbf
sparkplus/resource/EMD_202101/TL_SCCO_EMD.prj
sparkplus/resource/EMD_202101/TL_SCCO_EMD.shp
sparkplus/resource/EMD_202101/TL_SCCO_EMD.shx
sparkplus/resource/LI_202101/TL_SCCO_LI.dbf
sparkplus/resource/LI_202101/TL_SCCO_LI.prj
sparkplus/resource/LI_202101/TL_SCCO_LI.shp
sparkplus/resource/LI_202101/TL_SCCO_LI.shx
sparkplus/resource/data/daegu_streetlight.csv
sparkplusTest-0.9.8.dist-info/LICENSE
sparkplusTest-0.9.8.dist-info/METADATA
sparkplusTest-0.9.8.dist-info/WHEEL
sparkplusTest-0.9.8.dist-info/top_level.txt
sparkplusTest-0.9.8.dist-info/RECORD
